__init__.py
mask_stars_NIRISS.py
mask_stars_NIRISS-2024.11.11.dist-info/LICENSE.md
mask_stars_NIRISS-2024.11.11.dist-info/METADATA
mask_stars_NIRISS-2024.11.11.dist-info/WHEEL
mask_stars_NIRISS-2024.11.11.dist-info/top_level.txt
mask_stars_NIRISS-2024.11.11.dist-info/RECORD
