Metadata-Version: 2.1
Name: mask_stars_NIRISS
Version: 2024.11.11
Summary: Mask stars in JWST NIRISS images
Author-email: Zackary Hutchens <zhutchen@unca.edu>
Maintainer-email: Zackary Hutchens <zhutchen@unca.edu>
License: MIT License
Project-URL: Homepage, https://github.com/zhutchens1/NIRISS-star-masks/
Project-URL: Repository, https://github.com/zhutchens1/NIRISS-star-masks/
Requires-Python: >=3.8
License-File: LICENSE.md
Requires-Dist: numpy
Requires-Dist: pandas
Requires-Dist: matplotlib
Requires-Dist: astropy
Requires-Dist: astroquery
Requires-Dist: grizli
Requires-Dist: pathos
Requires-Dist: opencv-python
Requires-Dist: tqdm
